nature/__init__.py
nature-0.0.1.dist-info/LICENSE.txt
nature-0.0.1.dist-info/METADATA
nature-0.0.1.dist-info/WHEEL
nature-0.0.1.dist-info/top_level.txt
nature-0.0.1.dist-info/RECORD
