Metadata-Version: 2.1
Name: nature
Version: 0.0.1
Summary: A python package for nature inspired algorithms
Home-page: UNKNOWN
Author: Kyle Erwin
Author-email: kyle.erwin24@gmail.com
License: UNKNOWN
Platform: UNKNOWN
Classifier: Programming Language :: Python :: 3 :: Only
Classifier: Programming Language :: Python :: 3.6
Classifier: Programming Language :: Python :: 3.7
Classifier: Programming Language :: Python :: 3.8
Classifier: Programming Language :: Python :: 3.9
Classifier: License :: OSI Approved :: MIT License
Classifier: Operating System :: OS Independent
Provides-Extra: dev
Requires-Dist: pytest (>=3.7) ; extra == 'dev'
Requires-Dist: tox ; extra == 'dev'
